se3_group/.DS_Store
se3_group/__init__.py
se3_group/definitions.py
se3_group/se3.py
se3_group-0.1.3.dist-info/LICENSE
se3_group-0.1.3.dist-info/METADATA
se3_group-0.1.3.dist-info/WHEEL
se3_group-0.1.3.dist-info/RECORD
